LICENSE
README.md
setup.py
hammer/__init__.py
hammer/io.py
hammer/log.py
hammer/lr.py
hammer/metric.py
hammer/model_checkpoint.py
hammer/model_summary.py
hammer/image/__init__.py
hammer/image/color.py
hammer/image/medical_image_window_transform.py
hammer/image/overlay.py
hammer/loss/__init__.py
hammer/loss/dice_loss.py
hammer/model/__init__.py
hammer/model/unet.py
hammer/sampler/__init__.py
hammer/sampler/coordinate_generator.py
hammer/sampler/data_loader.py
hammer/sampler/grid_sampler.py
hammer/sampler/patch_picker.py
hammer/sampler/three_dim_dataset.py
hammer/sampler/util.py
nnhammer.egg-info/PKG-INFO
nnhammer.egg-info/SOURCES.txt
nnhammer.egg-info/dependency_links.txt
nnhammer.egg-info/requires.txt
nnhammer.egg-info/top_level.txt