Metadata-Version: 2.1
Name: nnhammer
Version: 1.0.8
Summary: My hammer.
Author: Dai Jian
Author-email: daijian@stumail.ysu.edu.cn
Classifier: Programming Language :: Python :: 3.7
Classifier: License :: OSI Approved :: GNU General Public License v3 (GPLv3)
Classifier: Operating System :: OS Independent
Requires-Python: ~=3.7
License-File: LICENSE
